.gitignore
HISTORY.txt
README.rst
setup.py
version.txt
imageretriever/__init__.py
imageretriever/admin.py
imageretriever/forms.py
imageretriever/models.py
imageretriever/urls.py
imageretriever/utils.py
imageretriever/views.py
imageretriever.egg-info/PKG-INFO
imageretriever.egg-info/SOURCES.txt
imageretriever.egg-info/dependency_links.txt
imageretriever.egg-info/not-zip-safe
imageretriever.egg-info/requires.txt
imageretriever.egg-info/top_level.txt