Metadata-Version: 1.0
Name: imageretriever
Version: 0.1
Summary: A Django package to download missing images on your local instance from the production/preview server.
Home-page: http://zestsoftware.nl
Author: Zest Software
Author-email: info@zestsoftware.nl
License: GPL
Platform: UNKNOWN
Classifier: Programming Language :: Python
Classifier: Framework :: Django
